cpeparser/__init__.py
cpeparser/cpe.py
cpeparser/errors.py
cpeparser/parser.py
cpeparser/test_cpe.py
cpeparser-0.0.2.dist-info/WHEEL
cpeparser-0.0.2.dist-info/METADATA
cpeparser-0.0.2.dist-info/RECORD
