Metadata-Version: 2.1
Name: cpeparser
Version: 0.0.2
Summary: CPE - Common platform enumeration parser in Python
Home-page: https://github.com/sabuhish/cpe-parser
License: MIT
Author: sabuhish
Author-email: sabuhi.shukurov@gmail.com
Requires-Python: >=3.8.12,<4.0.0
Classifier: Intended Audience :: Developers
Classifier: License :: OSI Approved :: MIT License
Classifier: Operating System :: OS Independent
Classifier: Programming Language :: Python
Classifier: Programming Language :: Python :: 3
Classifier: Programming Language :: Python :: 3 :: Only
Classifier: Programming Language :: Python :: 3.10
Classifier: Programming Language :: Python :: 3.6
Classifier: Programming Language :: Python :: 3.7
Classifier: Programming Language :: Python :: 3.9
Project-URL: Repository, https://github.com/sabuhish/cpe-parser
